{
  "quote": {
    "price": 297.73,
    "change": -5.9,
    "changePercent": -1.9432,
    "high": 302.37,
    "low": 296.51,
    "open": 302.01,
    "previousClose": 303.63
  },
  "earnings": [
    {
      "actual": 5.23,
      "estimate": 5.0539,
      "period": "2025-12-31",
      "quarter": 4,
      "surprise": 0.1761,
      "surprisePercent": 3.4844,
      "symbol": "JPM",
      "year": 2025
    },
    {
      "actual": 5.07,
      "estimate": 4.8839,
      "period": "2025-09-30",
      "quarter": 3,
      "surprise": 0.1861,
      "surprisePercent": 3.8105,
      "symbol": "JPM",
      "year": 2025
    },
    {
      "actual": 4.96,
      "estimate": 4.5268,
      "period": "2025-06-30",
      "quarter": 2,
      "surprise": 0.4332,
      "surprisePercent": 9.5697,
      "symbol": "JPM",
      "year": 2025
    },
    {
      "actual": 4.91,
      "estimate": 4.66,
      "period": "2025-03-31",
      "quarter": 1,
      "surprise": 0.25,
      "surprisePercent": 5.3648,
      "symbol": "JPM",
      "year": 2025
    }
  ],
  "recommendations": {
    "buy": 15,
    "hold": 9,
    "period": "2026-01-01",
    "sell": 1,
    "strongBuy": 4,
    "strongSell": 1,
    "symbol": "JPM"
  },
  "source": "finnhub",
  "generatedAt": "2026-01-25T17:19:47.061Z"
}